openstack_flavor_manager/__init__.py
openstack_flavor_manager/main.py
openstack_flavor_manager-0.20251021.0.dist-info/licenses/LICENSE
openstack_flavor_manager-0.20251021.0.dist-info/METADATA
openstack_flavor_manager-0.20251021.0.dist-info/WHEEL
openstack_flavor_manager-0.20251021.0.dist-info/entry_points.txt
openstack_flavor_manager-0.20251021.0.dist-info/top_level.txt
openstack_flavor_manager-0.20251021.0.dist-info/RECORD
