Metadata-Version: 2.4
Name: openstack-flavor-manager
Version: 0.20251021.0
Summary: OpenStack flavor manager
Author-email: OSISM community <info@osism.tech>
License:                                  Apache License
Project-URL: Homepage, https://github.com/osism/openstack-flavor-manager
Project-URL: Bug Tracker, https://github.com/osism/openstack-flavor-manager/issues
Classifier: Development Status :: 5 - Production/Stable
Classifier: Environment :: Console
Classifier: Intended Audience :: Information Technology
Classifier: License :: OSI Approved :: Apache Software License
Classifier: Operating System :: OS Independent
Classifier: Programming Language :: Python
Classifier: Programming Language :: Python :: 3 :: Only
Classifier: Programming Language :: Python :: 3
Classifier: Programming Language :: Python :: 3.8
Classifier: Programming Language :: Python :: 3.9
Classifier: Programming Language :: Python :: 3.10
Classifier: Programming Language :: Python :: 3.11
Requires-Python: >=3.8
License-File: LICENSE
Requires-Dist: PyYAML==6.0.3
Requires-Dist: loguru==0.7.3
Requires-Dist: openstacksdk==4.7.1
Requires-Dist: requests-file==2.1.0
Requires-Dist: requests==2.32.5
Requires-Dist: typer[all]==0.20.0
Dynamic: license-file
